amulet_map_editor/__init__.py
amulet_map_editor/__main__.py
amulet_map_editor/__main_debug__.py
amulet_map_editor/_version.py
amulet_map_editor/__pyinstaller/__init__.py
amulet_map_editor/__pyinstaller/hook-amulet_map_editor.py
amulet_map_editor/__pyinstaller/hook-numpy.py
amulet_map_editor/api/__init__.py
amulet_map_editor/api/config.py
amulet_map_editor/api/datatypes.py
amulet_map_editor/api/lang.py
amulet_map_editor/api/resources.py
amulet_map_editor/api/framework/__init__.py
amulet_map_editor/api/framework/amulet_ui.py
amulet_map_editor/api/framework/app.py
amulet_map_editor/api/framework/base_tab.py
amulet_map_editor/api/framework/licence_dialog.py
amulet_map_editor/api/framework/update_check.py
amulet_map_editor/api/framework/warning_dialog.py
amulet_map_editor/api/framework/pages/__init__.py
amulet_map_editor/api/framework/pages/base_page.py
amulet_map_editor/api/framework/pages/main_menu.py
amulet_map_editor/api/framework/pages/world_page.py
amulet_map_editor/api/framework/programs/__init__.py
amulet_map_editor/api/framework/programs/about_program.py
amulet_map_editor/api/framework/programs/base_program.py
amulet_map_editor/api/image/__init__.py
amulet_map_editor/api/image/icon/tablericons/accessible.png
amulet_map_editor/api/image/icon/tablericons/adjustments.png
amulet_map_editor/api/image/icon/tablericons/alert_circle.png
amulet_map_editor/api/image/icon/tablericons/alert_triangle.png
amulet_map_editor/api/image/icon/tablericons/align_center.png
amulet_map_editor/api/image/icon/tablericons/align_justified.png
amulet_map_editor/api/image/icon/tablericons/align_left.png
amulet_map_editor/api/image/icon/tablericons/align_right.png
amulet_map_editor/api/image/icon/tablericons/anchor.png
amulet_map_editor/api/image/icon/tablericons/aperture.png
amulet_map_editor/api/image/icon/tablericons/apps.png
amulet_map_editor/api/image/icon/tablericons/archive.png
amulet_map_editor/api/image/icon/tablericons/arrow_back.png
amulet_map_editor-0.10.49.dist-info/licenses/LICENSE
amulet_map_editor-0.10.49.dist-info/METADATA
amulet_map_editor-0.10.49.dist-info/WHEEL
amulet_map_editor-0.10.49.dist-info/entry_points.txt
amulet_map_editor-0.10.49.dist-info/top_level.txt
amulet_map_editor-0.10.49.dist-info/RECORD
