Metadata-Version: 2.4
Name: amulet-map-editor
Version: 0.10.49
Summary: A new Minecraft world editor and converter that supports all versions since Java 1.12 and Bedrock 1.7.
Home-page: https://www.amuletmc.com
Author: James Clare, Ben Gothard et al.
Author-email: amuleteditor@gmail.com
Platform: any
Classifier: Programming Language :: Python :: 3
Classifier: Operating System :: OS Independent
Requires-Python: >=3.10
License-File: LICENSE
Requires-Dist: Pillow>=10.0.1
Requires-Dist: wxPython
Requires-Dist: numpy~=1.17
Requires-Dist: pyopengl~=3.0
Requires-Dist: packaging
Requires-Dist: amulet-core>=1.9.35,~=1.9
Requires-Dist: amulet-nbt~=2.0
Requires-Dist: pymctranslate~=1.2
Requires-Dist: minecraft-resource-pack~=1.3
Requires-Dist: platformdirs~=3.1
Provides-Extra: docs
Requires-Dist: Sphinx>=1.7.4; extra == "docs"
Requires-Dist: sphinx-autodoc-typehints>=1.3.0; extra == "docs"
Requires-Dist: sphinx_rtd_theme>=0.3.1; extra == "docs"
Provides-Extra: dev
Requires-Dist: black>=22.3; extra == "dev"
Requires-Dist: pre_commit>=1.11.1; extra == "dev"
Dynamic: license-file
